fruitpedia/__init__.py
fruitpedia/cli.py
fruitpedia/data.py
fruitpedia/search.py
fruitpedia-0.1.3.dist-info/licenses/LICENSE.txt
fruitpedia-0.1.3.dist-info/METADATA
fruitpedia-0.1.3.dist-info/WHEEL
fruitpedia-0.1.3.dist-info/entry_points.txt
fruitpedia-0.1.3.dist-info/top_level.txt
fruitpedia-0.1.3.dist-info/RECORD
