Metadata-Version: 2.4
Name: fruitpedia
Version: 0.1.3
Summary: A CLI library for fruit data lookup and filtering
Home-page: https://github.com/yourusername/fruitpedia
Author: Ningappa Kanavi
Author-email: Ningappa Kanavi <ningskanavi89@gmail.com>
License: MIT
Requires-Python: >=3.8
License-File: LICENSE.txt
Requires-Dist: click>=8.0
Requires-Dist: rich
Requires-Dist: pandas
Requires-Dist: rapidfuzz
Provides-Extra: dev
Requires-Dist: pytest; extra == "dev"
Requires-Dist: black; extra == "dev"
Requires-Dist: ruff; extra == "dev"
Dynamic: author
Dynamic: home-page
Dynamic: license-file
